permuted_brunnermunzel/__init__.py
permuted_brunnermunzel/brunnermunzel_test.py
permuted_brunnermunzel/py.typed
permuted_brunnermunzel-0.1.0.dist-info/licenses/LICENSE
permuted_brunnermunzel-0.1.0.dist-info/METADATA
permuted_brunnermunzel-0.1.0.dist-info/WHEEL
permuted_brunnermunzel-0.1.0.dist-info/top_level.txt
permuted_brunnermunzel-0.1.0.dist-info/RECORD
