Metadata-Version: 2.4
Name: permuted_brunnermunzel
Version: 0.1.0
Summary: Python implementation of the permuted Brunner-Munzel test for small sample sizes
Author-email: Matthew Corney <matthew_corney@yahoo.co.uk>
License: MIT
Project-URL: Homepage, https://github.com/MatthewCorney/permuted_brunner_munzel
Project-URL: Bug Tracker, https://github.com/MatthewCorney/permuted_brunner_munzel/issues
Project-URL: Documentation, https://github.com/MatthewCorney/permuted_brunner_munzel#readme
Keywords: statistics,brunner-munzel,nonparametric,hypothesis-testing
Classifier: Development Status :: 4 - Beta
Classifier: Intended Audience :: Science/Research
Classifier: Topic :: Scientific/Engineering :: Mathematics
Classifier: Programming Language :: Python :: 3
Classifier: Programming Language :: Python :: 3.8
Classifier: Programming Language :: Python :: 3.9
Classifier: Programming Language :: Python :: 3.10
Classifier: Programming Language :: Python :: 3.11
Classifier: Programming Language :: Python :: 3.12
Classifier: License :: OSI Approved :: MIT License
Classifier: Operating System :: OS Independent
Classifier: Typing :: Typed
Requires-Python: >=3.8
License-File: LICENSE
Requires-Dist: numpy<3.0,>=1.20
Requires-Dist: scipy<2.0,>=1.7
Provides-Extra: dev
Requires-Dist: pytest>=7.0; extra == "dev"
Requires-Dist: pytest-cov>=4.0; extra == "dev"
Requires-Dist: mypy>=1.0; extra == "dev"
Requires-Dist: ruff>=0.1.0; extra == "dev"
Dynamic: license-file
